mrdevtools/__init__.py
mrdevtools/logtools.py
mrdevtools/version.py
mrdevtools-0.1.0.dist-info/LICENSE
mrdevtools-0.1.0.dist-info/METADATA
mrdevtools-0.1.0.dist-info/WHEEL
mrdevtools-0.1.0.dist-info/top_level.txt
mrdevtools-0.1.0.dist-info/RECORD
