Metadata-Version: 2.1
Name: mrdevtools
Version: 0.1.0
Summary: mrdevtools - Python Library with tools to help developers.
Home-page: https://anatas_ch.gitlab.io/pyl_mrdevtools/
Author: Michael Rippstein
Author-email: info@anatas.ch
License: AGPL-3.0
Project-URL: Documentation, https://mrdevtools.readthedocs.io/
Project-URL: Bug Tracker, https://gitlab.com/anatas_ch/pyl_mrdevtools/-/issues
Project-URL: Source Code, https://gitlab.com/anatas_ch/pyl_mrdevtools
Platform: UNKNOWN
Classifier: Development Status :: 3 - Alpha
Classifier: Intended Audience :: Developers
Classifier: License :: OSI Approved :: GNU Affero General Public License v3 or later (AGPLv3+)
Classifier: Programming Language :: Python :: 3
Classifier: Programming Language :: Python :: 3.9
Classifier: Programming Language :: Python :: Implementation :: CPython
Classifier: Programming Language :: Python :: Implementation :: PyPy
Classifier: Operating System :: OS Independent
Classifier: Typing :: Typed
Requires-Python: >=3.9
License-File: LICENSE
Requires-Dist: colorama (>=0.4.3)
